{
  "name": "src",
  "type": "directory",
  "children": [
    {
      "name": "App.css",
      "type": "file"
    },
    {
      "name": "App.tsx",
      "type": "file"
    },
    {
      "name": "components",
      "type": "directory",
      "children": [
        {
          "name": "About.tsx",
          "type": "file"
        },
        {
          "name": "contact",
          "type": "directory",
          "children": [
            {
              "name": "ContactForm.tsx",
              "type": "file"
            },
            {
              "name": "ContactInfo.tsx",
              "type": "file"
            }
          ]
        },
        {
          "name": "Contact.tsx",
          "type": "file"
        },
        {
          "name": "Footer.tsx",
          "type": "file"
        },
        {
          "name": "Header.tsx",
          "type": "file"
        },
        {
          "name": "hero",
          "type": "directory",
          "children": [
            {
              "name": "jobTitles.ts",
              "type": "file"
            }
          ]
        },
        {
          "name": "Hero.tsx",
          "type": "file"
        },
        {
          "name": "projects",
          "type": "directory",
          "children": [
            {
              "name": "ProjectCard.tsx",
              "type": "file"
            },
            {
              "name": "ProjectFilter.tsx",
              "type": "file"
            },
            {
              "name": "projectsData.ts",
              "type": "file"
            },
            {
              "name": "types.ts",
              "type": "file"
            }
          ]
        },
        {
          "name": "Projects.tsx",
          "type": "file"
        },
        {
          "name": "ThemeSwitcher.tsx",
          "type": "file"
        },
        {
          "name": "ui",
          "type": "directory",
          "children": [
            {
              "name": "accordion.tsx",
              "type": "file"
            },
            {
              "name": "alert-dialog.tsx",
              "type": "file"
            },
            {
              "name": "alert.tsx",
              "type": "file"
            },
            {
              "name": "aspect-ratio.tsx",
              "type": "file"
            },
            {
              "name": "avatar.tsx",
              "type": "file"
            },
            {
              "name": "badge.tsx",
              "type": "file"
            },
            {
              "name": "breadcrumb.tsx",
              "type": "file"
            },
            {
              "name": "button.tsx",
              "type": "file"
            },
            {
              "name": "calendar.tsx",
              "type": "file"
            },
            {
              "name": "card.tsx",
              "type": "file"
            },
            {
              "name": "carousel.tsx",
              "type": "file"
            },
            {
              "name": "chart.tsx",
              "type": "file"
            },
            {
              "name": "checkbox.tsx",
              "type": "file"
            },
            {
              "name": "collapsible.tsx",
              "type": "file"
            },
            {
              "name": "command.tsx",
              "type": "file"
            },
            {
              "name": "context-menu.tsx",
              "type": "file"
            },
            {
              "name": "dialog.tsx",
              "type": "file"
            },
            {
              "name": "drawer.tsx",
              "type": "file"
            },
            {
              "name": "dropdown-menu.tsx",
              "type": "file"
            },
            {
              "name": "form.tsx",
              "type": "file"
            },
            {
              "name": "hover-card.tsx",
              "type": "file"
            },
            {
              "name": "input-otp.tsx",
              "type": "file"
            },
            {
              "name": "input.tsx",
              "type": "file"
            },
            {
              "name": "label.tsx",
              "type": "file"
            },
            {
              "name": "menubar.tsx",
              "type": "file"
            },
            {
              "name": "navigation-menu.tsx",
              "type": "file"
            },
            {
              "name": "pagination.tsx",
              "type": "file"
            },
            {
              "name": "popover.tsx",
              "type": "file"
            },
            {
              "name": "progress.tsx",
              "type": "file"
            },
            {
              "name": "radio-group.tsx",
              "type": "file"
            },
            {
              "name": "resizable.tsx",
              "type": "file"
            },
            {
              "name": "scroll-area.tsx",
              "type": "file"
            },
            {
              "name": "select.tsx",
              "type": "file"
            },
            {
              "name": "separator.tsx",
              "type": "file"
            },
            {
              "name": "sheet.tsx",
              "type": "file"
            },
            {
              "name": "sidebar.tsx",
              "type": "file"
            },
            {
              "name": "skeleton.tsx",
              "type": "file"
            },
            {
              "name": "slider.tsx",
              "type": "file"
            },
            {
              "name": "sonner.tsx",
              "type": "file"
            },
            {
              "name": "switch.tsx",
              "type": "file"
            },
            {
              "name": "table.tsx",
              "type": "file"
            },
            {
              "name": "tabs.tsx",
              "type": "file"
            },
            {
              "name": "textarea.tsx",
              "type": "file"
            },
            {
              "name": "toast.tsx",
              "type": "file"
            },
            {
              "name": "toaster.tsx",
              "type": "file"
            },
            {
              "name": "toggle-group.tsx",
              "type": "file"
            },
            {
              "name": "toggle.tsx",
              "type": "file"
            },
            {
              "name": "tooltip.tsx",
              "type": "file"
            },
            {
              "name": "use-toast.ts",
              "type": "file"
            }
          ]
        }
      ]
    },
    {
      "name": "hooks",
      "type": "directory",
      "children": [
        {
          "name": "use-mobile.tsx",
          "type": "file"
        },
        {
          "name": "use-toast.ts",
          "type": "file"
        }
      ]
    },
    {
      "name": "index.css",
      "type": "file"
    },
    {
      "name": "lib",
      "type": "directory",
      "children": [
        {
          "name": "utils.ts",
          "type": "file"
        }
      ]
    },
    {
      "name": "main.tsx",
      "type": "file"
    },
    {
      "name": "pages",
      "type": "directory",
      "children": [
        {
          "name": "Index.tsx",
          "type": "file"
        },
        {
          "name": "NotFound.tsx",
          "type": "file"
        }
      ]
    },
    {
      "name": "vite-env.d.ts",
      "type": "file"
    }
  ]
}